odoo/addons/sale_order_line_tag/README.rst
odoo/addons/sale_order_line_tag/__init__.py
odoo/addons/sale_order_line_tag/__manifest__.py
odoo/addons/sale_order_line_tag/i18n/es.po
odoo/addons/sale_order_line_tag/i18n/it.po
odoo/addons/sale_order_line_tag/i18n/sale_order_line_tag.pot
odoo/addons/sale_order_line_tag/models/__init__.py
odoo/addons/sale_order_line_tag/models/sale_order_line.py
odoo/addons/sale_order_line_tag/models/sale_order_line_tag.py
odoo/addons/sale_order_line_tag/readme/CONTRIBUTORS.md
odoo/addons/sale_order_line_tag/readme/DESCRIPTION.md
odoo/addons/sale_order_line_tag/security/ir.model.access.csv
odoo/addons/sale_order_line_tag/static/description/icon.png
odoo/addons/sale_order_line_tag/static/description/index.html
odoo/addons/sale_order_line_tag/tests/__init__.py
odoo/addons/sale_order_line_tag/tests/test_sale_order_line_tag.py
odoo/addons/sale_order_line_tag/views/sale_order_views.xml
odoo_addon_sale_order_line_tag-18.0.1.0.0.2.dist-info/METADATA
odoo_addon_sale_order_line_tag-18.0.1.0.0.2.dist-info/WHEEL
odoo_addon_sale_order_line_tag-18.0.1.0.0.2.dist-info/top_level.txt
odoo_addon_sale_order_line_tag-18.0.1.0.0.2.dist-info/RECORD
